trch/__init__.py
trch/main.py
trch-0.2.0.dist-info/METADATA
trch-0.2.0.dist-info/WHEEL
trch-0.2.0.dist-info/top_level.txt
trch-0.2.0.dist-info/RECORD
