Metadata-Version: 2.1
Name: trch
Version: 0.2.0
Classifier: Programming Language :: Python :: 3
Classifier: License :: OSI Approved :: MIT License
Classifier: Operating System :: OS Independent
Requires-Python: >=3.6
Requires-Dist: pyperclip (>=1.8.2)
